aes/sbox.sv
module sbox
    (
    input wire clk,
    input wire [7:0] x,
    output logic [7:0] y,
    output logic [7:0] my_x
    );

    // Isomorphic mapping

    logic [7:0] mapped;
    isomorphic_map map(.x(x), .y(mapped));

    // Reg
    logic [3:0] high_0, low_0, h_xor_l_0;
    logic [7:0] x_0;
    always_ff @(posedge clk ) begin
        high_0 <= mapped[7:4];
        h_xor_l_0 <= mapped[7:4] ^ mapped[3:0];
        low_0 <= mapped[3:0];
        x_0 <= x;
    end

    // Stage 1
    logic [3:0] stage_1_lambda, stage_1_square;
    gf_2_4_square square(.x(high_0), .y(stage_1_square));
    gf_2_4_lamba_mult lambda(.x(stage_1_square), .y(stage_1_lambda));
    // gf_2_4_lamba_square_comp comp(.x(high_0), .y(stage_1_map));

    logic [3:0] stage_1_prod;
    spem stage_1_mul(.H(h_xor_l_0), .B(low_0), .prod(stage_1_prod));

    // Reg
    logic [3:0] high_1, h_xor_l_1, prod_xor_map_1;
    logic [7:0] x_1;
    always_ff @(posedge clk ) begin
        high_1 <= high_0;
        h_xor_l_1 <= h_xor_l_0;
        prod_xor_map_1 <= stage_1_lambda ^ stage_1_prod;
        x_1 <= x_0;
    end

    // Stage 2

    logic [3:0] inv;
    simpl inverse(.x(prod_xor_map_1), .y(inv));

    // Reg
    logic [3:0] high_2, h_xor_l_2, inv_2;
    logic [7:0] x_2;
    always_ff @(posedge clk ) begin
        high_2 <= high_1;
        h_xor_l_2 <= h_xor_l_1;
        inv_2 <= inv;
        x_2 <= x_1;
    end

    // Stage 3
    logic [3:0] high_prod;
    spem high_mul(.H(high_2), .B(inv_2), .prod(high_prod));

    logic [3:0] low_prod;
    spem low_mul(.H(h_xor_l_2), .B(inv_2), .prod(low_prod));

    // Reg

    logic [3:0] high_3, low_3;
    logic [7:0] x_3;
    always_ff @(posedge clk ) begin
        high_3 <= high_prod;
        low_3 <= low_prod;
        x_3 <= x_2;
    end


    // Inverse Mapping and Affine

    logic [7:0] affine_inverse_iso_map;
    affine_inverse_iso aff(.x({high_3, low_3}), .y(affine_inverse_iso_map));

    // Reg

    logic [7:0] out;
    logic [7:0] x_4;
    always_ff @(posedge clk ) begin
        out <= affine_inverse_iso_map;
        y <= out;
        x_4 <= x_3;
        my_x <= x_4;
    end

endmodule: sbox

// module gf_2_4_lamba_square_comp
//     (
//     input wire [3:0] x,
//     output logic [3:0] y
//     );

//     assign y = {x[0], x[3] ^ x[2] ^ x[1] ^ x[0], x[3], x[3] ^ x[1]};

// endmodule: gf_2_4_lamba_square_comp

module gf_2_4_lamba_mult
    (
    input wire [3:0] x,
    output logic [3:0] y
    );

    assign y = {x[2] ^ x[0], x[3] ^ x[2] ^ x[1] ^ x[0], x[3], x[2]};

endmodule: gf_2_4_lamba_mult

module gf_2_4_square
    (
    input wire [3:0] x,
    output logic [3:0] y
    );

    assign y = {x[3], x[3] ^ x[2], x[2] ^ x[1], x[3] ^ x[1] ^ x[0]};

endmodule: gf_2_4_square

module isomorphic_map
    (
    input wire [7:0] x,
    output logic [7:0] y
    );

    always_comb begin
        y[7] = x[7]^x[5];
        y[6] = x[7]^x[6]^x[4]^x[3]^x[2]^x[1];
        y[5] = x[7]^x[5]^x[3]^x[2];
        y[4] = x[7]^x[5]^x[3]^x[2]^x[1];
        y[3] = x[7]^x[6]^x[2]^x[1];
        y[2] = x[7]^x[4]^x[3]^x[2]^x[1];
        y[1] = x[6]^x[4]^x[1];
        y[0] = x[6]^x[1]^x[0];
    end

endmodule: isomorphic_map

module affine_inverse_iso
    (
    input wire [7:0] x,
    output logic [7:0] y
    );

    always_comb begin
        y[7] = x[7]^x[3]^x[2];
        y[6] = x[7]^x[6]^x[5]^x[4];
        y[5] = x[7]^x[2];
        y[4] = x[7]^x[4]^x[1]^x[0];
        y[3] = x[2]^x[1]^x[0];
        y[2] = x[6]^x[5]^x[4]^x[3]^x[2]^x[0];
        y[1] = x[7]^x[0];
        y[0] = x[7]^x[6]^x[2]^x[1]^x[0];
        y ^= 'h63;
    end    

endmodule: affine_inverse_iso

aes/spem.sv
`default_nettype none
// A GF(2^4) multiplier
module spem
    (
    input wire [3:0] H,
    input wire [3:0] B,
    output logic [3:0] prod
    );

    logic [1:0] w_0, w_1, w_2;

    w0 block0(.H_H(H[3:2]), .B_H(B[3:2]), .w(w_0));

    w1 block1(.H(H), .B(B), .w(w_1));

    w2 block2(.H_L(H[1:0]), .B_L(B[1:0]), .w(w_2));

    assign prod = {w_1 ^ w_2, w_0 ^ w_2};
endmodule: spem

module w0
    (
    input wire [3:2] H_H,
    input wire [1:0] B_H,
    output logic [1:0] w
    );

    always_comb begin
        case (B_H)
            2'b00: w = 2'b00;
            2'b01: w = {H_H[3]^H_H[2], H_H[3]};
            2'b10: w = {H_H[2], H_H[3]^H_H[2]};
            2'b11: w = H_H;
        endcase
    end


endmodule: w0

module w1
    (
    input wire [3:0] H,
    input wire [3:0] B,
    output logic [1:0] w
    );

    logic [1:0] H_xor;
    logic [1:0] B_xor;

    always_comb begin
        H_xor = H[3:2] ^ H[1:0];
        B_xor = B[3:2] ^ B[1:0];

        case (B_xor)
            2'b00: w = 2'b00;
            2'b01: w = H_xor;
            2'b10: w = {H_xor[1]^H_xor[0], H_xor[1]};
            2'b11: w = {H_xor[0], H_xor[1]^H_xor[0]};
        endcase
    end

endmodule: w1

module w2
    (
    input wire [1:0] H_L,
    input wire [1:0] B_L,
    output logic [1:0] w
    );

    always_comb begin
        case (B_L)
            2'b00: w = 2'b00;
            2'b01: w = H_L;
            2'b10: w = {H_L[1]^H_L[0], H_L[1]};
            2'b11: w = {H_L[0], H_L[1]^H_L[0]};
        endcase
    end

endmodule: w2

aes/simpl.sv
/*
    Implements inverse of x over GF(2^4)
*/
module simpl
    (
    input wire [3:0] x,
    output logic [3:0] y
    );
    
always_comb begin
    y[0] = x[3]&x[2]&x[1] ^ x[3]&x[2]&x[0] ^ x[3]&x[1] 
         ^ x[3]&x[1]&x[0] ^ x[3]&x[0]      ^ x[2] 
         ^ x[2]&x[1]      ^ x[2]&x[1]&x[0] ^ x[1]
         ^ x[0];

    y[1] = x[3]&x[2]&x[1] ^ x[3]&x[1]&x[0] ^ x[3]
         ^ x[2]           ^ x[2]&x[0]      ^ x[1];

    y[2] = x[3]&x[2]&x[1] ^ x[3]&x[2]&x[0] ^ x[3]&x[0]
         ^ x[2]           ^ x[2]&x[1];
    
    y[3] = x[3]&x[0]      ^ x[3]&x[2]&x[1] ^ x[3] 
         ^ x[2];

end

endmodule: simpl

aes/sbox_tb.sv
`timescale 1ns/1ps

module sbox_tb ();
    logic clock;

    always begin
        #2.5;
        clock = 0;
        #2.5;
        clock = 1;
    end
    
    logic [7:0] x,y,my_x;

    sbox dut (
        .clk(clock),
        .x(x),
        .y(y),
        .my_x(my_x)
    );

    initial begin
        $dumpfile("sbox.test.vcd");
        $dumpvars(0, sbox_tb);
        $display("----- sbox Unit Test -----");
        x = 'h00;
    end

    always_ff @(posedge clock) begin
        x <= x + 1;
       // $display("in: %h", x);
    end 

    always_ff @(posedge clock) begin
        $display("out: y: %h my_x: %h", y, my_x);
        if (my_x == 'hFF) begin
            $finish;
        end
    end



endmodule: sbox_tb

aes/sbox.test.vcd
$date
	Tue Apr  9 19:18:51 2024
$end
$version
	Icarus Verilog
$end
$timescale
	1ps
$end
$scope module sbox_tb $end
$var wire 8 ! y [7:0] $end
$var wire 8 " my_x [7:0] $end
$var reg 1 # clock $end
$var reg 8 $ x [7:0] $end
$scope module dut $end
$var wire 1 # clk $end
$var wire 8 % x [7:0] $end
$var wire 4 & stage_1_square [3:0] $end
$var wire 4 ' stage_1_prod [3:0] $end
$var wire 4 ( stage_1_lambda [3:0] $end
$var wire 8 ) mapped [7:0] $end
$var wire 4 * low_prod [3:0] $end
$var wire 4 + inv [3:0] $end
$var wire 4 , high_prod [3:0] $end
$var wire 8 - affine_inverse_iso_map [7:0] $end
$var reg 4 . h_xor_l_0 [3:0] $end
$var reg 4 / h_xor_l_1 [3:0] $end
$var reg 4 0 h_xor_l_2 [3:0] $end
$var reg 4 1 high_0 [3:0] $end
$var reg 4 2 high_1 [3:0] $end
$var reg 4 3 high_2 [3:0] $end
$var reg 4 4 high_3 [3:0] $end
$var reg 4 5 inv_2 [3:0] $end
$var reg 4 6 low_0 [3:0] $end
$var reg 4 7 low_3 [3:0] $end
$var reg 8 8 my_x [7:0] $end
$var reg 8 9 out [7:0] $end
$var reg 4 : prod_xor_map_1 [3:0] $end
$var reg 8 ; x_0 [7:0] $end
$var reg 8 < x_1 [7:0] $end
$var reg 8 = x_2 [7:0] $end
$var reg 8 > x_3 [7:0] $end
$var reg 8 ? x_4 [7:0] $end
$var reg 8 @ y [7:0] $end
$scope module aff $end
$var wire 8 A x [7:0] $end
$var reg 8 B y [7:0] $end
$upscope $end
$scope module high_mul $end
$var wire 4 C B [3:0] $end
$var wire 4 D H [3:0] $end
$var wire 2 E w_2 [1:0] $end
$var wire 2 F w_1 [1:0] $end
$var wire 2 G w_0 [1:0] $end
$var wire 4 H prod [3:0] $end
$scope module block0 $end
$var wire 2 I B_H [1:0] $end
$var wire 2 J H_H [3:2] $end
$var reg 2 K w [1:0] $end
$upscope $end
$scope module block1 $end
$var wire 4 L B [3:0] $end
$var wire 4 M H [3:0] $end
$var reg 2 N B_xor [1:0] $end
$var reg 2 O H_xor [1:0] $end
$var reg 2 P w [1:0] $end
$upscope $end
$scope module block2 $end
$var wire 2 Q B_L [1:0] $end
$var wire 2 R H_L [1:0] $end
$var reg 2 S w [1:0] $end
$upscope $end
$upscope $end
$scope module inverse $end
$var wire 4 T x [3:0] $end
$var reg 4 U y [3:0] $end
$upscope $end
$scope module lambda $end
$var wire 4 V y [3:0] $end
$var wire 4 W x [3:0] $end
$upscope $end
$scope module low_mul $end
$var wire 4 X B [3:0] $end
$var wire 4 Y H [3:0] $end
$var wire 2 Z w_2 [1:0] $end
$var wire 2 [ w_1 [1:0] $end
$var wire 2 \ w_0 [1:0] $end
$var wire 4 ] prod [3:0] $end
$scope module block0 $end
$var wire 2 ^ B_H [1:0] $end
$var wire 2 _ H_H [3:2] $end
$var reg 2 ` w [1:0] $end
$upscope $end
$scope module block1 $end
$var wire 4 a B [3:0] $end
$var wire 4 b H [3:0] $end
$var reg 2 c B_xor [1:0] $end
$var reg 2 d H_xor [1:0] $end
$var reg 2 e w [1:0] $end
$upscope $end
$scope module block2 $end
$var wire 2 f B_L [1:0] $end
$var wire 2 g H_L [1:0] $end
$var reg 2 h w [1:0] $end
$upscope $end
$upscope $end
$scope module map $end
$var wire 8 i x [7:0] $end
$var reg 8 j y [7:0] $end
$upscope $end
$scope module square $end
$var wire 4 k x [3:0] $end
$var wire 4 l y [3:0] $end
$upscope $end
$scope module stage_1_mul $end
$var wire 4 m B [3:0] $end
$var wire 4 n H [3:0] $end
$var wire 2 o w_2 [1:0] $end
$var wire 2 p w_1 [1:0] $end
$var wire 2 q w_0 [1:0] $end
$var wire 4 r prod [3:0] $end
$scope module block0 $end
$var wire 2 s B_H [1:0] $end
$var wire 2 t H_H [3:2] $end
$var reg 2 u w [1:0] $end
$upscope $end
$scope module block1 $end
$var wire 4 v B [3:0] $end
$var wire 4 w H [3:0] $end
$var reg 2 x B_xor [1:0] $end
$var reg 2 y H_xor [1:0] $end
$var reg 2 z w [1:0] $end
$upscope $end
$scope module block2 $end
$var wire 2 { B_L [1:0] $end
$var wire 2 | H_L [1:0] $end
$var reg 2 } w [1:0] $end
$upscope $end
$upscope $end
$upscope $end
$upscope $end
$enddefinitions $end
$comment Show the parameter values. $end
$dumpall
$end
#0
$dumpvars
bx }
bx |
bx {
bx z
bx y
bx x
bx w
bx v
bx u
bx t
bx s
bx r
bx q
bx p
bx o
bx n
bx m
bx l
bx k
b0 j
b0 i
bx h
bx g
bx f
bx e
bx d
bx c
bx b
bx a
bx `
bx _
bx ^
bx ]
bx \
bx [
bx Z
bx Y
bx X
bx W
bx V
bx U
bx T
bx S
bx R
bx Q
bx P
bx O
bx N
bx M
bx L
bx K
bx J
bx I
bx H
bx G
bx F
bx E
bx D
bx C
bx B
bx A
bx @
bx ?
bx >
bx =
bx <
bx ;
bx :
bx 9
bx 8
bx 7
bx 6
bx 5
bx 4
bx 3
bx 2
bx 1
bx 0
bx /
bx .
bx -
bx ,
bx +
bx *
b0 )
bx (
bx '
bx &
b0 %
b0 $
x#
bx "
bx !
$end
#2500
0#
#5000
b0 '
b0 r
b0 (
b0 V
b0 q
b0 u
b0 o
b0 }
b0 &
b0 W
b0 l
b0 s
b0 {
b0 t
b0 |
b0 p
b0 z
b0 x
b0 y
b1 )
b1 j
b0 ;
b0 6
b0 m
b0 v
b0 .
b0 n
b0 w
b0 1
b0 k
b1 $
b1 %
b1 i
1#
#7500
0#
#10000
b1 '
b1 r
b1 o
b1 }
b1011111 )
b1011111 j
b0 +
b0 U
b1 {
b1 |
b1 p
b1 z
b1 x
b1 y
b10 $
b10 %
b10 i
b0 <
b0 :
b0 T
b0 /
b0 2
b1 ;
b1 6
b1 m
b1 v
b1 .
b1 n
b1 w
1#
#12500
0#
#15000
b101 (
b101 V
b0 *
b0 ]
b0 ,
b0 H
b111 '
b111 r
b111 &
b111 W
b111 l
b10 q
b10 u
b0 \
b0 `
b0 Z
b0 h
b0 G
b0 K
b0 E
b0 S
b11 s
b11 {
b10 t
b10 |
b0 p
b0 z
b0 x
b0 y
b1 +
b1 U
b0 I
b0 Q
b0 ^
b0 f
b0 _
b0 g
b0 [
b0 e
b0 c
b0 d
b0 J
b0 R
b0 F
b0 P
b0 N
b0 O
b1011110 )
b1011110 j
b10 ;
b1111 6
b1111 m
b1111 v
b1010 .
b1010 n
b1010 w
b101 1
b101 k
b1 <
b1 :
b1 T
b1 /
b0 =
b0 5
b0 C
b0 L
b0 X
b0 a
b0 0
b0 Y
b0 b
b0 3
b0 D
b0 M
b11 $
b11 %
b11 i
1#
#17500
0#
#20000
b1 *
b1 ]
b11 '
b11 r
b1100011 -
b1100011 B
b1 Z
b1 h
b1111100 )
b1111100 j
b0 A
b1 Q
b1 N
b1 f
b1 g
b1 [
b1 e
b1 c
b1 d
b11 +
b11 U
b10 {
b11 |
b1 p
b1 z
b1 x
b1 y
b100 $
b100 %
b100 i
b0 >
b0 7
b0 4
b1 =
b1 5
b1 C
b1 L
b1 X
b1 a
b1 0
b1 Y
b1 b
b10 <
b10 :
b10 T
b1010 /
b101 2
b11 ;
b1110 6
b1110 m
b1110 v
b1011 .
b1011 n
b1011 w
1#
#22500
0#
#25000
b1101 (
b1101 V
b1111 ,
b1111 H
b1110 '
b1110 r
b100 &
b100 W
b100 l
b101 *
b101 ]
b0 o
b0 }
b11 E
b11 S
b1111100 -
b1111100 B
b0 {
b11 p
b11 z
b11 x
b1001 +
b1001 U
b11 Q
b11 f
b10 _
b10 g
b0 [
b0 e
b11 c
b0 d
b1 J
b1 R
b11 N
b1 A
b1111101 )
b1111101 j
b100 ;
b1100 6
b1100 m
b1100 v
b111 1
b111 k
b11 <
b110 :
b110 T
b1011 /
b10 =
b11 5
b11 C
b11 L
b11 X
b11 a
b1010 0
b1010 Y
b1010 b
b101 3
b101 D
b101 M
b1 >
b1 7
b0 ?
b1100011 9
b101 $
b101 %
b101 i
1#
#27500
0#
#30000
b110 ,
b110 H
b10 *
b10 ]
b1000 '
b1000 r
b1110111 -
b1110111 B
b11 G
b11 K
b1 E
b1 S
b1 \
b1 `
b11 Z
b11 h
b10 o
b10 }
b100011 )
b100011 j
b11110101 A
b10 I
b1 Q
b10 ^
b1 f
b11 g
b11 [
b11 e
b1 d
b10 +
b10 U
b1 {
b10 |
b0 p
b0 z
b10 x
b0 y
b110 $
b110 %
b110 i
b0 "
b0 8
b1 ?
b1100011 !
b1100011 @
b1111100 9
b10 >
b101 7
b1111 4
b11 =
b1001 5
b1001 C
b1001 L
b1001 X
b1001 a
b1011 0
b1011 Y
b1011 b
b100 <
b11 :
b11 T
b111 2
b101 ;
b1101 6
b1101 m
b1101 v
b1010 .
b1010 n
b1010 w
1#
#32500
0#
#35000
b1000 (
b1000 V
b11 '
b11 r
b11 &
b11 W
b11 l
b1101 *
b1101 ]
b1001 ,
b1001 H
b0 q
b0 u
b11 o
b11 }
b0 G
b0 K
b0 \
b0 `
b1 Z
b1 h
b1111011 -
b1111011 B
b0 s
b11 {
b0 t
b1 |
b11 p
b11 z
b11 x
b1 y
b1100 +
b1100 U
b0 I
b10 Q
b0 ^
b10 f
b10 [
b10 e
b10 c
b11 R
b11 F
b11 P
b10 N
b10 O
b1100010 A
b100010 )
b100010 j
b110 ;
b11 6
b11 m
b11 v
b1 .
b1 n
b1 w
b10 1
b10 k
b101 <
b101 :
b101 T
b1010 /
b100 =
b10 5
b10 C
b10 L
b10 X
b10 a
b111 3
b111 D
b111 M
b11 >
b10 7
b110 4
b1 "
b1 8
b10 ?
b1111100 !
b1111100 @
b1110111 9
b111 $
b111 %
b111 i
1#
#37500
0#
#40000
b101 ,
b101 H
b10 *
b10 ]
b0 '
b0 r
b11110010 -
b11110010 B
b1 G
b1 K
b0 E
b0 S
b10 \
b10 `
b0 Z
b0 h
b0 o
b0 }
b1110100 )
b1110100 j
b10011101 A
b11 I
b0 Q
b1 F
b1 P
b11 N
b11 ^
b0 f
b10 g
b0 [
b0 e
b11 c
b0 d
b111 +
b111 U
b10 {
b0 |
b0 p
b0 z
b10 x
b0 y
b1000 $
b1000 %
b1000 i
b10 "
b10 8
b11 ?
b1110111 !
b1110111 @
b1111011 9
b100 >
b1101 7
b1001 4
b101 =
b1100 5
b1100 C
b1100 L
b1100 X
b1100 a
b1010 0
b1010 Y
b1010 b
b110 <
b1011 :
b1011 T
b1 /
b10 2
b111 ;
b10 6
b10 m
b10 v
b0 .
b0 n
b0 w
1#
#42500
0#
#45000
b1101 (
b1101 V
b1100 '
b1100 r
b100 &
b100 W
b100 l
b111 *
b111 ]
b1001 ,
b1001 H
b0 \
b0 `
b11 Z
b11 h
b0 G
b0 K
b1 E
b1 S
b1101011 -
b1101011 B
b1 s
b0 {
b11 |
b11 p
b11 z
b1 x
b11 y
b1010 +
b1010 U
b1 I
b11 Q
b1 ^
b11 f
b0 _
b1 g
b10 [
b10 e
b10 c
b1 d
b0 J
b10 R
b11 F
b11 P
b10 N
b1010010 A
b1110101 )
b1110101 j
b1000 ;
b100 6
b100 m
b100 v
b11 .
b11 n
b11 w
b111 1
b111 k
b111 <
b1000 :
b1000 T
b0 /
b110 =
b111 5
b111 C
b111 L
b111 X
b111 a
b1 0
b1 Y
b1 b
b10 3
b10 D
b10 M
b101 >
b10 7
b101 4
b11 "
b11 8
b100 ?
b1111011 !
b1111011 @
b11110010 9
b1001 $
b1001 %
b1001 i
1#
#47500
0#
#50000
b1111 ,
b1111 H
b0 *
b0 ]
b1010 '
b1010 r
b1101111 -
b1101111 B
b11 E
b11 S
b0 Z
b0 h
b10 o
b10 }
b101011 )
b101011 j
b10010111 A
b10 I
b10 Q
b0 F
b0 P
b0 N
b10 ^
b10 f
b0 g
b0 [
b0 e
b0 c
b0 d
b1 +
b1 U
b1 {
b10 |
b0 p
b0 z
b0 x
b10 y
b1010 $
b1010 %
b1010 i
b100 "
b100 8
b101 ?
b11110010 !
b11110010 @
b1101011 9
b110 >
b111 7
b1001 4
b111 =
b1010 5
b1010 C
b1010 L
b1010 X
b1010 a
b0 0
b0 Y
b0 b
b1000 <
b1 :
b1 T
b11 /
b111 2
b1001 ;
b101 6
b101 m
b101 v
b10 .
b10 n
b10 w
1#
#52500
0#
#55000
b1000 (
b1000 V
b10 '
b10 r
b11 &
b11 W
b11 l
b11 *
b11 ]
b111 ,
b111 H
b1 q
b1 u
b11 o
b11 }
b11 Z
b11 h
b11000101 -
b11000101 B
b10 s
b11 {
b10 t
b1 |
b11 p
b11 z
b1 x
b11 y
b1011 +
b1011 U
b0 I
b1 Q
b0 ^
b1 f
b11 g
b11 [
b11 e
b1 c
b11 d
b1 J
b11 R
b10 F
b10 P
b1 N
b11110000 A
b101010 )
b101010 j
b1010 ;
b1011 6
b1011 m
b1011 v
b1001 .
b1001 n
b1001 w
b10 1
b10 k
b1001 <
b111 :
b111 T
b10 /
b1000 =
b1 5
b1 C
b1 L
b1 X
b1 a
b11 0
b11 Y
b11 b
b111 3
b111 D
b111 M
b111 >
b0 7
b1111 4
b101 "
b101 8
b110 ?
b1101011 !
b1101011 @
b1101111 9
b1011 $
b1011 %
b1011 i
1#
#57500
0#
#60000
b1 ,
b1 H
b1101 *
b1101 ]
b1 '
b1 r
b110000 -
b110000 B
b11 G
b11 K
b10 E
b10 S
b1 Z
b1 h
b0 o
b0 }
b1000 )
b1000 j
b1110011 A
b10 I
b11 Q
b10 ^
b11 f
b10 g
b10 [
b10 e
b10 d
b1000 +
b1000 U
b10 {
b0 |
b0 p
b0 z
b0 x
b10 y
b1100 $
b1100 %
b1100 i
b110 "
b110 8
b111 ?
b1101111 !
b1101111 @
b11000101 9
b1000 >
b11 7
b111 4
b1001 =
b1011 5
b1011 C
b1011 L
b1011 X
b1011 a
b10 0
b10 Y
b10 b
b1010 <
b1010 :
b1010 T
b1001 /
b10 2
b1011 ;
b1010 6
b1010 m
b1010 v
b1000 .
b1000 n
b1000 w
1#
#62500
0#
#65000
b0 (
b0 V
b1101 '
b1101 r
b0 &
b0 W
b0 l
b101 *
b101 ]
b1100 ,
b1100 H
b1 \
b1 `
b0 Z
b0 h
b0 G
b0 K
b0 E
b0 S
b1 -
b1 B
b0 {
b11 p
b11 z
b10 x
b110 +
b110 U
b0 Q
b0 f
b10 _
b1 g
b1 [
b1 e
b10 c
b11 d
b0 J
b10 R
b11 F
b11 P
b10 N
b11101 A
b1001 )
b1001 j
b1100 ;
b1000 6
b1000 m
b1000 v
b0 1
b0 k
b1011 <
b1001 :
b1001 T
b1000 /
b1010 =
b1000 5
b1000 C
b1000 L
b1000 X
b1000 a
b1001 0
b1001 Y
b1001 b
b10 3
b10 D
b10 M
b1001 >
b1101 7
b1 4
b111 "
b111 8
b1000 ?
b11000101 !
b11000101 @
b110000 9
b1101 $
b1101 %
b1101 i
1#
#67500
0#
#70000
b111 *
b111 ]
b1011 ,
b1011 H
b1100 '
b1100 r
b1100111 -
b1100111 B
b11 E
b11 S
b11 \
b11 `
b1 o
b1 }
b1010111 )
b1010111 j
b11000101 A
b1 I
b10 Q
b1 F
b1 P
b11 N
b1 ^
b10 f
b0 g
b11 c
b10 d
b1110 +
b1110 U
b1 {
b1 |
b10 p
b10 z
b11 x
b11 y
b1110 $
b1110 %
b1110 i
b1000 "
b1000 8
b1001 ?
b110000 !
b110000 @
b1 9
b1010 >
b101 7
b1100 4
b1011 =
b110 5
b110 C
b110 L
b110 X
b110 a
b1000 0
b1000 Y
b1000 b
b1100 <
b1101 :
b1101 T
b0 2
b1101 ;
b1001 6
b1001 m
b1001 v
b1001 .
b1001 n
b1001 w
1#
#72500
0#
#75000
b101 (
b101 V
b1001 '
b1001 r
b111 &
b111 W
b111 l
b1010 *
b1010 ]
b0 ,
b0 H
b0 q
b0 u
b10 \
b10 `
b0 E
b0 S
b101011 -
b101011 B
b1 s
b11 {
b0 t
b10 |
b11 p
b11 z
b10 x
b10 y
b101 +
b101 U
b11 I
b11 ^
b10 [
b10 e
b1 c
b0 R
b0 F
b0 P
b1 N
b0 O
b10110111 A
b1010110 )
b1010110 j
b1110 ;
b111 6
b111 m
b111 v
b10 .
b10 n
b10 w
b101 1
b101 k
b1101 <
b1100 :
b1100 T
b1001 /
b1100 =
b1110 5
b1110 C
b1110 L
b1110 X
b1110 a
b0 3
b0 D
b0 M
b1011 >
b111 7
b1011 4
b1001 "
b1001 8
b1010 ?
b1 !
b1 @
b1100111 9
b1111 $
b1111 %
b1111 i
1#
#77500
0#
#80000
b110 *
b110 ]
b1101 '
b1101 r
b11111110 -
b11111110 B
b11 \
b11 `
b1 Z
b1 h
b1000110 )
b1000110 j
b1010 A
b1 I
b1 Q
b0 N
b1 ^
b1 f
b1 g
b0 [
b0 e
b0 c
b11 d
b10 {
b11 |
b10 p
b10 z
b11 x
b11 y
b10000 $
b10000 %
b10000 i
b1010 "
b1010 8
b1011 ?
b1100111 !
b1100111 @
b101011 9
b1100 >
b1010 7
b0 4
b1101 =
b101 5
b101 C
b101 L
b101 X
b101 a
b1001 0
b1001 Y
b1001 b
b1110 <
b10 /
b101 2
b1111 ;
b110 6
b110 m
b110 v
b11 .
b11 n
b11 w
1#
#82500
0#
#85000
b1001 (
b1001 V
b1010 *
b1010 ]
b111 ,
b111 H
b1011 '
b1011 r
b110 &
b110 W
b110 l
b11 o
b11 }
b0 \
b0 `
b10 Z
b10 h
b10 G
b10 K
b1 E
b1 S
b11010111 -
b11010111 B
b10 |
b1 p
b1 z
b10 y
b1010 +
b1010 U
b0 _
b10 g
b10 d
b1 J
b1 R
b110 A
b1000111 )
b1000111 j
b10000 ;
b10 .
b10 n
b10 w
b100 1
b100 k
b1111 <
b1000 :
b1000 T
b11 /
b1110 =
b10 0
b10 Y
b10 b
b101 3
b101 D
b101 M
b1101 >
b110 7
b1011 "
b1011 8
b1100 ?
b101011 !
b101011 @
b11111110 9
b10001 $
b10001 %
b10001 i
1#
#87500
0#
#90000
b1001 ,
b1001 H
b101 *
b101 ]
b1110 '
b1110 r
b10101011 -
b10101011 B
b11 G
b11 K
b10 E
b10 S
b1 Z
b1 h
b10 o
b10 }
b11001 )
b11001 j
b1111010 A
b10 I
b10 Q
b10 ^
b10 f
b11 g
b11 d
b11 +
b11 U
b11 {
b11 |
b10 x
b11 y
b10010 $
b10010 %
b10010 i
b1100 "
b1100 8
b1101 ?
b11111110 !
b11111110 @
b11010111 9
b1110 >
b1010 7
b111 4
b1111 =
b1010 5
b1010 C
b1010 L
b1010 X
b1010 a
b11 0
b11 Y
b11 b
b10000 <
b10 :
b10 T
b10 /
b100 2
b10001 ;
b111 6
b111 m
b111 v
b11 .
b11 n
b11 w
1#
#92500
0#
#95000
b1100 (
b1100 V
b101 '
b101 r
b1 &
b1 W
b1 l
b1 *
b1 ]
b1100 ,
b1100 H
b1 q
b1 u
b0 o
b0 }
b0 G
b0 K
b0 E
b0 S
b1110110 -
b1110110 B
b10 s
b1 {
b10 t
b0 |
b11 x
b10 y
b1011 +
b1011 U
b0 I
b11 Q
b0 ^
b11 f
b10 g
b1 [
b1 e
b11 c
b10 d
b0 R
b11 F
b11 P
b11 N
b1 O
b10010101 A
b11000 )
b11000 j
b10010 ;
b1001 6
b1001 m
b1001 v
b1000 .
b1000 n
b1000 w
b1 1
b1 k
b10001 <
b111 :
b111 T
b11 /
b10000 =
b11 5
b11 C
b11 L
b11 X
b11 a
b10 0
b10 Y
b10 b
b100 3
b100 D
b100 M
b1111 >
b101 7
b1001 4
b1101 "
b1101 8
b1110 ?
b11010111 !
b11010111 @
b10101011 9
b10011 $
b10011 %
b10011 i
1#
#97500
0#
#100000
b111 ,
b111 H
b110 *
b110 ]
b11001010 -
b11001010 B
b11 G
b11 K
b10 Z
b10 h
b111010 )
b111010 j
b11000001 A
b10 I
b1 F
b1 P
b1 N
b10 ^
b11 g
b11 [
b11 e
b1 c
b11 d
b110 +
b110 U
b0 {
b1 |
b10 x
b11 y
b10100 $
b10100 %
b10100 i
b1110 "
b1110 8
b1111 ?
b10101011 !
b10101011 @
b1110110 9
b10000 >
b1 7
b1100 4
b10001 =
b1011 5
b1011 C
b1011 L
b1011 X
b1011 a
b11 0
b11 Y
b11 b
b10010 <
b1001 :
b1001 T
b1000 /
b1 2
b10011 ;
b1000 6
b1000 m
b1000 v
b1001 .
b1001 n
b1001 w
1#
#102500
0#
#105000
b100 (
b100 V
b1011 '
b1011 r
b10 &
b10 W
b10 l
b111 *
b111 ]
b110 ,
b110 H
b10 o
b10 }
b11 \
b11 `
b0 Z
b0 h
b0 G
b0 K
b10 E
b10 S
b10000010 -
b10000010 B
b10 {
b0 p
b0 z
b0 x
b1 I
b10 Q
b1 ^
b10 f
b10 _
b0 g
b1 [
b1 e
b11 c
b10 d
b0 J
b1 R
b11 F
b11 P
b11 N
b1110110 A
b111011 )
b111011 j
b10100 ;
b1010 6
b1010 m
b1010 v
b11 1
b11 k
b10011 <
b1001 /
b10010 =
b110 5
b110 C
b110 L
b110 X
b110 a
b1000 0
b1000 Y
b1000 b
b1 3
b1 D
b1 M
b10001 >
b110 7
b111 4
b1111 "
b1111 8
b10000 ?
b1110110 !
b1110110 @
b11001010 9
b10101 $
b10101 %
b10101 i
1#
#107500
0#
#110000
b1 *
b1 ]
b1001 '
b1001 r
b11001001 -
b11001001 B
b10 Z
b10 h
b0 o
b0 }
b1100101 )
b1100101 j
b1100111 A
b1 g
b10 [
b10 e
b11 d
b100 +
b100 U
b11 {
b0 |
b10 p
b10 z
b1 x
b10 y
b10110 $
b10110 %
b10110 i
b10000 "
b10000 8
b10001 ?
b11001010 !
b11001010 @
b10000010 9
b10010 >
b111 7
b110 4
b10011 =
b1001 0
b1001 Y
b1001 b
b10100 <
b1111 :
b1111 T
b11 2
b10101 ;
b1011 6
b1011 m
b1011 v
b1000 .
b1000 n
b1000 w
1#
#112500
0#
